[{"sku": "389192011", "name": "Morrisons 2 Anti Allergy Medium Back Sleeper Pillows", "brand": {"id": "108397", "name": "Morrisons"}, "catchWeight": "2 per pack", "price": {"current": 8.0, "lpp": false, "unit": {"price": 4.0, "per": "each"}, "type": "REGULAR"}, "mainCategory": "Home & Garden/Bedroom/Pillows", "image": {"hash": "c8a6d80009de548bccad542ccf5e35e2"}, "reviewStats": {"averageRate": 3.0, "count": 1}, "packInfo": {}, "type": "REGULAR", "gtin": "5010525172330", "hash": -2129907603}, {"sku": "391385011", "name": "Morrisosn Indigo Reversible Bath Mat", "brand": {"id": "108397", "name": "Morrisons"}, "price": {"current": 8.0, "lpp": false, "unit": {"price": 0.0, "per": "each"}, "type": "REGULAR"}, "mainCategory": "Home & Garden/Bathroom/Towel, Bathrobes & Bath Mats", "image": {"hash": "564c555775a6d2c6bc1a31e9734ad15a"}, "packInfo": {}, "type": "REGULAR", "gtin": "5010251666691", "hash": 452503465}, {"sku": "394571011", "name": "Pyrex Magic 6 Cup Muffin Tin 23cm", "brand": {"id": "156340", "name": "Pyrex"}, "price": {"current": 8.0, "lpp": false, "unit": {"price": 8.0, "per": "each"}, "type": "REGULAR"}, "mainCategory": "Home & Garden/Kitchen/Baking & Preserving/Baking Tins & Trays", "image": {"hash": "67aaf89b425ad93143bb433f3eba19e8"}, "reviewStats": {"averageRate": 1.0, "count": 1}, "packInfo": {}, "type": "REGULAR", "gtin": "3426470276405", "hash": -1821230254}, {"sku": "404417011", "name": "Ravenhead Entertain Gin Balloon Glasses Set ", "brand": {"id": "1003911320", "name": "Ravenhead"}, "catchWeight": "2 per pack", "price": {"current": 8.0, "lpp": false, "unit": {"price": 4.0, "per": "each"}, "type": "REGULAR"}, "mainCategory": "Drinks/Mixers & Adult Soft Drinks", "image": {"hash": "2f8860b5a7c5e541321ac10e025a9b4a"}, "packInfo": {}, "type": "REGULAR", "gtin": "5010853253114", "hash": 933756004}, {"sku": "407223011", "name": "Gorilla Super Glue Brush & Nozzle 12G", "brand": {"id": "165771", "name": "Gorilla"}, "catchWeight": "12g", "price": {"current": 8.0, "lpp": false, "unit": {"price": 6.67, "per": "per 10g"}, "type": "REGULAR"}, "mainCategory": "Home & Garden/Stationery & Home Office/Adhesives & Tape/Glue", "image": {"hash": "9fcdacbfd88cc1546f531a3400743c1f"}, "reviewStats": {"averageRate": 3.299999952316284, "count": 3}, "packInfo": {}, "type": "REGULAR", "gtin": "5704947002480", "hash": -1907579937}, {"sku": "412769011", "name": "Aqualona Nebula Shower Head Chrome", "brand": {"id": "170750", "name": "Aqualona"}, "price": {"current": 8.0, "lpp": false, "unit": {"price": 0.0, "per": "each"}, "type": "REGULAR"}, "mainCategory": "Home & Garden/Bathroom/Fixtures & Fittings", "image": {"hash": "bbfc8b03b6f1254362c8f73eea2dd10b"}, "reviewStats": {"averageRate": 3.0, "count": 2}, "packInfo": {}, "type": "REGULAR", "gtin": "5011264002278", "hash": -1257108884}, {"sku": "412822011", "name": "Duracell Sync & Charge Usb 3.0 Cable 1M ", "brand": {"id": "107307", "name": "Duracell"}, "price": {"current": 8.0, "lpp": false, "unit": {"price": 0.0, "per": "each"}, "type": "REGULAR"}, "mainCategory": "Home & Garden/Car Care & Accessories/Travel Accessories", "image": {"hash": "b5e6a3d94a20a0b3d16d07a1c9d2a2f5"}, "packInfo": {}, "type": "REGULAR", "gtin": "5055190175590", "hash": -938659417}, {"sku": "413143011", "name": "Tinc Hard Case Pencil Case Blue Octopus", "brand": {"id": "170849", "name": "Tinc"}, "price": {"current": 8.0, "lpp": false, "unit": {"price": 0.0, "per": "each"}, "type": "REGULAR"}, "mainCategory": "Home & Garden/Stationery & Home Office/Kids Stationery/Back to School", "image": {"hash": "59fb0468ef1c82ebab4722cf5bd2c6b6"}, "packInfo": {}, "type": "REGULAR", "gtin": "5055610323952", "hash": -198790896}, {"sku": "413153011", "name": "Tinc Starter Pack Blue Octopus", "brand": {"id": "170849", "name": "Tinc"}, "price": {"current": 8.0, "lpp": false, "unit": {"price": 0.0, "per": "each"}, "type": "REGULAR"}, "mainCategory": "Home & Garden/Stationery & Home Office/Kids Stationery/Back to School", "image": {"hash": "0c7620ec252babdfcf079e5fcde88c3a"}, "packInfo": {}, "type": "REGULAR", "gtin": "5055610324072", "hash": -1873133600}, {"sku": "413160011", "name": "Tinc Starter Pack Pink Cupcake", "brand": {"id": "170849", "name": "Tinc"}, "price": {"current": 8.0, "lpp": false, "unit": {"price": 0.0, "per": "each"}, "type": "REGULAR"}, "mainCategory": "Home & Garden/Stationery & Home Office/Kids Stationery/Back to School", "image": {"hash": "c906f960c8ed07cfb6a8e625ae95b6d7"}, "packInfo": {}, "type": "REGULAR", "gtin": "5055610324065", "hash": -584136388}, {"sku": "414786011", "name": "Brambles Floating Swan & Duck Food", "brand": {"id": "1005523313", "name": "Brambles"}, "catchWeight": "1.75kg", "price": {"current": 8.0, "lpp": false, "unit": {"price": 4.57, "per": "per kg"}, "type": "REGULAR"}, "mainCategory": "Pet Shop/Small Pets/Birds/Wild Bird Food", "image": {"hash": "7210213f7ef74a58bfa73d71ed2c9b79"}, "reviewStats": {"averageRate": 5.0, "count": 1}, "packInfo": {}, "type": "REGULAR", "gtin": "5060538620038", "hash": -1990233298}, {"sku": "420103011", "name": "Morrisons 100% Cotton Graphite Fitted Sheet Single", "brand": {"id": "108397", "name": "Morrisons"}, "price": {"current": 8.0, "lpp": false, "unit": {"price": 0.0, "per": "each"}, "type": "REGULAR"}, "mainCategory": "Home & Garden/Bedroom/Bedsheets", "image": {"hash": "e699bb5b4ca4a2122786352ee56c10b2"}, "packInfo": {}, "type": "REGULAR", "gtin": "5010251901563", "hash": 1517654829}, {"sku": "422180011", "name": "Staedtler Textsurfer Highlighter Set", "brand": {"id": "153460", "name": "Staedtler"}, "price": {"current": 8.0, "lpp": false, "unit": {"price": 8.0, "per": "each"}, "type": "REGULAR"}, "mainCategory": "Home & Garden/Stationery & Home Office/Pens & Pencils/Highlighters", "image": {"hash": "39eb7d50cc2844ac863314988f57793c"}, "packInfo": {}, "type": "REGULAR", "gtin": "4007817364178", "hash": -922884350}, {"sku": "438001011", "name": "Duracell Lithium Coin 2032 Batteries 3V (CR2032 / DL2032)", "brand": {"id": "108018", "name": "Duracell"}, "catchWeight": "4 per pack", "price": {"current": 8.0, "lpp": false, "unit": {"price": 2.0, "per": "each"}, "type": "REGULAR"}, "mainCategory": "Home & Garden/Batteries/Specialist Batteries", "image": {"hash": "cca4dc366a227869154962911f456591"}, "packInfo": {}, "type": "REGULAR", "gtin": "5000394119376", "hash": -1459819690}, {"sku": "438002011", "name": "Duracell Alkaline Button LR44 Batteries 1.5V (76A / A76 / V13GA)", "brand": {"id": "107307", "name": "Duracell"}, "catchWeight": "4 per pack", "price": {"current": 8.0, "lpp": false, "unit": {"price": 2.0, "per": "each"}, "type": "REGULAR"}, "mainCategory": "Home & Garden/Batteries/Specialist Batteries", "image": {"hash": "75bee80a7182dcc70a5187b297a2060f"}, "packInfo": {}, "type": "REGULAR", "gtin": "5000394019621", "hash": 1386958850}, {"sku": "442017011", "name": "Ravenhead Majestic Mixer Glasses Set 310ml", "brand": {"id": "1003911320", "name": "Ravenhead"}, "catchWeight": "4 per pack", "price": {"current": 8.0, "lpp": false, "unit": {"price": 2.0, "per": "each"}, "type": "REGULAR"}, "mainCategory": "Home & Garden/Dining/Glassware/Wine Glasses", "image": {"hash": "e431ac9eabf638307db66c2e132f4a8a"}, "packInfo": {}, "type": "REGULAR", "gtin": "5010853253343", "hash": 140681935}, {"sku": "444968011", "name": "Homefire Premium Hardwood Kiln Dried Logs", "brand": {"id": "173860", "name": "Homefire"}, "catchWeight": "18L", "price": {"current": 8.0, "lpp": false, "unit": {"price": 0.444, "per": "per litre"}, "type": "REGULAR"}, "mainCategory": "Home & Garden/BBQ, Garden & Outdoor Living/Fuels & Lighters", "image": {"hash": "c4fad74bf22dfde39b9ad6b052e74caa"}, "packInfo": {}, "type": "REGULAR", "gtin": "5017974003208", "hash": -1304251911}, {"sku": "449858011", "name": "Addis  70cm x 40cm Natural Helmsley Door Mat ", "brand": {"id": "160750", "name": "Addis"}, "price": {"current": 8.0, "lpp": false, "unit": {"price": 8.0, "per": "each"}, "type": "REGULAR"}, "mainCategory": "Home & Garden/Laundry, Cleaning & Storage/Doormats & Doorstops", "image": {"hash": "ae8e4a8064aaaa813e936dd3d6dcd293"}, "packInfo": {}, "type": "REGULAR", "gtin": "5010303160269", "hash": 301535374}, {"sku": "453073011", "name": "Morrisons Foam Kneeler Pad", "brand": {"id": "108397", "name": "Morrisons"}, "price": {"current": 8.0, "lpp": false, "unit": {"price": 0.0, "per": "each"}, "type": "REGULAR"}, "mainCategory": "Home & Garden/BBQ, Garden & Outdoor Living/Garden Tools & Watering/Tools", "image": {"hash": "a8acc31378cf3da4bc2f9fbf9fa75aad"}, "reviewStats": {"averageRate": 2.0, "count": 1}, "packInfo": {}, "type": "REGULAR", "gtin": "5010525104393", "hash": -1810206472}, {"sku": "471206011", "name": "Morrisons Stainless Steel Vacuum Flask", "brand": {"id": "108397", "name": "Morrisons"}, "price": {"current": 8.0, "lpp": false, "unit": {"price": 0.0, "per": "each"}, "type": "REGULAR"}, "mainCategory": "Home & Garden/Kitchen/Food & Drink Storage/Flasks, Jugs & Bottles ", "image": {"hash": "a177e3fe31d340f2bdf42bcd86cbd140"}, "packInfo": {}, "type": "REGULAR", "gtin": "5010251935124", "hash": 996791630}, {"sku": "472623011", "name": "Morrisons 100% Cotton White Fitted Sheet", "brand": {"id": "108397", "name": "Morrisons"}, "price": {"current": 8.0, "lpp": false, "unit": {"price": 0.0, "per": "each"}, "messageType": "FROM_GROUP", "type": "REGULAR"}, "mainCategory": "Home & Garden/Bedroom/Bedsheets", "image": {"hash": "e6558361accb788d8a83002cdd585a94", "sku": "383352011"}, "reviewStats": {"averageRate": 2.0, "count": 6}, "packInfo": {}, "type": "PRODUCT_GROUP_PARENT", "hash": 1022128608}, {"sku": "472624011", "name": "Morrisons 100% Cotton Grey Fitted Sheet", "brand": {"id": "108397", "name": "Morrisons"}, "price": {"current": 8.0, "lpp": false, "unit": {"price": 0.0, "per": "each"}, "messageType": "FROM_GROUP", "type": "REGULAR"}, "mainCategory": "Home & Garden/Bedroom/Bedsheets", "image": {"hash": "cca3869c89bfd88b95f798158dc1e43a", "sku": "382925011"}, "reviewStats": {"averageRate": 2.0, "count": 2}, "packInfo": {}, "type": "PRODUCT_GROUP_PARENT", "hash": 791962678}, {"sku": "480932011", "name": "Morrisons Travel Adaptor With Us Pin & Usb Connector", "brand": {"id": "108397", "name": "Morrisons"}, "price": {"current": 8.0, "lpp": false, "unit": {"price": 0.0, "per": "each"}, "type": "REGULAR"}, "mainCategory": "Home & Garden/DIY/Plugs & Extension Leads", "image": {"hash": "2e36a90e478b300c19f3427ab19fdbec"}, "packInfo": {}, "type": "REGULAR", "gtin": "5010525013879", "hash": 1951878233}, {"sku": "484072011", "name": "Morrisons 4 In 1 Mandolin Slicer", "brand": {"id": "108397", "name": "Morrisons"}, "price": {"current": 8.0, "lpp": false, "unit": {"price": 0.0, "per": "each"}, "type": "REGULAR"}, "mainCategory": "Home & Garden/Kitchen/Utensils & Food Preparation/Utensils", "image": {"hash": "b27c8363292bb73ac40845a0bc10e824"}, "reviewStats": {"averageRate": 1.0, "count": 1}, "packInfo": {}, "type": "REGULAR", "gtin": "5010251972204", "hash": -1263401954}, {"sku": "484185011", "name": "Morrisons Metallic Blue Food Flask 600Ml", "brand": {"id": "177837", "name": "Seal N Go"}, "price": {"current": 8.0, "lpp": false, "unit": {"price": 0.0, "per": "each"}, "type": "REGULAR"}, "mainCategory": "Home & Garden/Kitchen/Food & Drink Storage/Flasks, Jugs & Bottles ", "image": {"hash": "5124ee5651c6d6694cbf4148072146ea"}, "reviewStats": {"averageRate": 1.2999999523162842, "count": 6}, "packInfo": {}, "type": "REGULAR", "gtin": "5010251972976", "hash": 1065421777}, {"sku": "484380011", "name": "Morrisons Grey Pebble Tablemats", "brand": {"id": "108397", "name": "Morrisons"}, "catchWeight": "4 per pack", "price": {"current": 8.0, "lpp": false, "unit": {"price": 2.0, "per": "each"}, "type": "REGULAR"}, "mainCategory": "Home & Garden/Dining/Tableware", "image": {"hash": "3615e8f7b5e264d61414deb004fe6e21"}, "packInfo": {}, "type": "REGULAR", "gtin": "5010251977278", "hash": -952724960}, {"sku": "504233011", "name": "Morrisons Waxfill Lime In Clear Glass 2Pk", "brand": {"id": "108397", "name": "Morrisons"}, "price": {"current": 8.0, "lpp": false, "unit": {"price": 0.0, "per": "each"}, "type": "REGULAR"}, "mainCategory": "Home & Garden/Candles & Home Fragrance/Diffusers, Refills & Pot Pourri", "image": {"hash": "2e830f2dd6b5f352f344d365e8bc785d"}, "packInfo": {}, "type": "REGULAR", "gtin": "5010525044446", "hash": 1531132764}, {"sku": "504554011", "name": "Morrisons Salad Spinner", "brand": {"id": "108397", "name": "Morrisons"}, "price": {"current": 8.0, "lpp": false, "unit": {"price": 0.0, "per": "each"}, "type": "REGULAR"}, "mainCategory": "Home & Garden/Kitchen/Utensils & Food Preparation/Sieves & Colanders", "image": {"hash": "06c4424354708150c0797a0b3365feba"}, "reviewStats": {"averageRate": 3.0, "count": 2}, "packInfo": {}, "type": "REGULAR", "gtin": "5010251916949", "hash": 302072382}, {"sku": "507881011", "name": "Morrisons A4 Led White Light Box", "brand": {"id": "108397", "name": "Morrisons"}, "price": {"current": 8.0, "lpp": false, "unit": {"price": 0.0, "per": "each"}, "type": "REGULAR"}, "mainCategory": "Home & Garden/Living Room/Lighting ", "image": {"hash": "387e2c91f414d7174f7c7db59a865404"}, "reviewStats": {"averageRate": 5.0, "count": 1}, "packInfo": {}, "type": "REGULAR", "gtin": "5010525045214", "hash": 1587834133}, {"sku": "507888011", "name": "Morrisons 100% Cotton Sulpher Single Fitted Sheet", "brand": {"id": "108397", "name": "Morrisons"}, "price": {"current": 8.0, "lpp": false, "unit": {"price": 0.0, "per": "each"}, "type": "REGULAR"}, "mainCategory": "Home & Garden/Bedroom/Bedsheets", "image": {"hash": "8a2cfd1fc7bb717cb12c78941a3e6b19"}, "packInfo": {}, "type": "REGULAR", "gtin": "5010525044668", "hash": 610919133}, {"sku": "509530011", "name": "Croydex Silver Tile Shower Curtain", "brand": {"id": "181403", "name": "Norcross Group Holdings"}, "price": {"current": 8.0, "lpp": false, "unit": {"price": 0.0, "per": "each"}, "type": "REGULAR"}, "mainCategory": "Home & Garden/Bathroom/Shower Curtains", "image": {"hash": "3acefc1b77473d7211bd360ec7ffb1c3"}, "reviewStats": {"averageRate": 2.700000047683716, "count": 3}, "packInfo": {}, "type": "REGULAR", "gtin": "5012049666661", "hash": -1913455144}, {"sku": "511559011", "name": "Morrisons Unicorn Light", "brand": {"id": "108397", "name": "Morrisons"}, "price": {"current": 8.0, "lpp": false, "unit": {"price": 0.0, "per": "each"}, "type": "REGULAR"}, "mainCategory": "Home & Garden/Bedroom/Children's Bedroom", "image": {"hash": "b34bd30f8b792687bdeb2ff904fce6cd"}, "reviewStats": {"averageRate": 5.0, "count": 1}, "packInfo": {}, "type": "REGULAR", "gtin": "5010525046709", "hash": -548174640}, {"sku": "514705011", "name": "Sistema To Go Bento Lunch 1.65L", "brand": {"id": "156342", "name": "Sistema"}, "price": {"current": 8.0, "lpp": false, "unit": {"price": 0.0, "per": "each"}, "type": "REGULAR"}, "mainCategory": "Home & Garden/Kitchen/Food & Drink Storage/Food Containers", "image": {"hash": "7c182ec3636498744bba1d964169f3d4"}, "packInfo": {}, "type": "REGULAR", "gtin": "9414202216908", "hash": 1088106383}, {"sku": "526849011", "name": "Nutmeg Medium Back sleep 2 Ultrasoft Pillows", "brand": {"id": "160193", "name": "Nutmeg"}, "price": {"current": 8.0, "lpp": false, "unit": {"price": 0.0, "per": "each"}, "type": "REGULAR"}, "mainCategory": "Home & Garden/Bedroom/Pillows", "image": {"hash": "4133595d5118431c5e7b6a453a54541e"}, "packInfo": {}, "type": "REGULAR", "gtin": "5010525172323", "hash": 1270925530}, {"sku": "526851011", "name": "Morrisons Ultrasoft Waterproof Mattress Protector Single", "brand": {"id": "108397", "name": "Morrisons"}, "price": {"current": 8.0, "lpp": false, "unit": {"price": 0.0, "per": "each"}, "type": "REGULAR"}, "mainCategory": "Home & Garden/Bedroom/Mattress Protectors", "image": {"hash": "1253b583ec285f4845f0321ac1911e41"}, "reviewStats": {"averageRate": 5.0, "count": 1}, "packInfo": {}, "type": "REGULAR", "gtin": "5010525054001", "hash": 1241258167}, {"sku": "526857011", "name": "Morrisons Orthopaedic Support Pillow", "brand": {"id": "108397", "name": "Morrisons"}, "price": {"current": 8.0, "lpp": false, "unit": {"price": 0.0, "per": "each"}, "type": "REGULAR"}, "mainCategory": "Home & Garden/Bedroom/Pillows", "image": {"hash": "1a64482ce585c550cee22ca4a8546eb0"}, "reviewStats": {"averageRate": 3.700000047683716, "count": 3}, "packInfo": {}, "type": "REGULAR", "gtin": "5010525053844", "hash": -1167820408}, {"sku": "526893011", "name": "Home Essentials Double Duvet 10.5 Tog", "brand": {"id": "186278", "name": "Morrisons Home Essentials"}, "price": {"current": 8.0, "lpp": false, "unit": {"price": 0.0, "per": "each"}, "type": "REGULAR"}, "mainCategory": "More Ways To Save/Prices Locked Low", "image": {"hash": "2676a2cc633c21fe5bf7fc115a8d9328"}, "reviewStats": {"averageRate": 5.0, "count": 1}, "packInfo": {}, "type": "REGULAR", "gtin": "5010525052960", "hash": -1087140715}, {"sku": "533420011", "name": "Morrisons Magnolia & Velvet Peony Reed Diffuser", "brand": {"id": "108397", "name": "Morrisons"}, "catchWeight": "150ml", "price": {"current": 8.0, "lpp": false, "unit": {"price": 0.533, "per": "per 10ml"}, "type": "REGULAR"}, "mainCategory": "Home & Garden/Candles & Home Fragrance/Diffusers, Refills & Pot Pourri", "image": {"hash": "80a36550a6f12c428e6f9a498edc527e"}, "packInfo": {}, "type": "REGULAR", "gtin": "5010525052649", "hash": 1737573938}, {"sku": "533424011", "name": "Morrisons Wire Pot Pourri", "brand": {"id": "108397", "name": "Morrisons"}, "price": {"current": 8.0, "lpp": false, "unit": {"price": 0.0, "per": "each"}, "type": "REGULAR"}, "mainCategory": "Home & Garden/Candles & Home Fragrance/Diffusers, Refills & Pot Pourri", "image": {"hash": "b7882687a90416d67b4bfdd341677443"}, "reviewStats": {"averageRate": 5.0, "count": 1}, "packInfo": {}, "type": "REGULAR", "gtin": "5010525087337", "hash": -1825917218}, {"sku": "533598011", "name": "Morrisons Grey Ribbed Double Toothbrush Holder", "brand": {"id": "108397", "name": "Morrisons"}, "price": {"current": 8.0, "lpp": false, "unit": {"price": 0.0, "per": "each"}, "type": "REGULAR"}, "mainCategory": "Home & Garden/Bathroom/Bathroom Accessories", "image": {"hash": "9f4f4b6c65f67a7c43e3808685d8710c"}, "packInfo": {}, "type": "REGULAR", "gtin": "5010525053455", "hash": 1335636433}, {"sku": "533600011", "name": "Morrisons Grey Striped Supersoft Bath Mat", "brand": {"id": "108397", "name": "Morrisons"}, "price": {"current": 8.0, "lpp": false, "unit": {"price": 0.0, "per": "each"}, "type": "REGULAR"}, "mainCategory": "Home & Garden/Bathroom/Towel, Bathrobes & Bath Mats", "image": {"hash": "b07a43f952c587c3d182e8fef6825c2d"}, "reviewStats": {"averageRate": 1.0, "count": 1}, "packInfo": {}, "type": "REGULAR", "gtin": "5010525053240", "hash": -11317430}, {"sku": "533602011", "name": "Morrisons Silver Grey Reversible Bath Mat", "brand": {"id": "108397", "name": "Morrisons"}, "price": {"current": 8.0, "lpp": false, "unit": {"price": 0.0, "per": "each"}, "type": "REGULAR"}, "mainCategory": "Home & Garden/Bathroom/Towel, Bathrobes & Bath Mats", "image": {"hash": "ef74778fc0760ac84297f0566f8e6c84"}, "packInfo": {}, "type": "REGULAR", "gtin": "5010251814368", "hash": -1082401019}, {"sku": "533615011", "name": "Morrisons Stainless Steel 3 Cup Cafetiere", "brand": {"id": "108397", "name": "Morrisons"}, "price": {"current": 8.0, "lpp": false, "unit": {"price": 0.0, "per": "each"}, "type": "REGULAR"}, "mainCategory": "Home & Garden/Dining/Cafetiere, Teapots & Accessories ", "image": {"hash": "f97af204342a6846b05c917be96a4afc"}, "packInfo": {}, "type": "REGULAR", "gtin": "5010525062143", "hash": 1869055783}, {"sku": "534126011", "name": "Gorilla Super Glue 15G", "brand": {"id": "165771", "name": "Gorilla"}, "catchWeight": "15g", "price": {"current": 8.0, "lpp": false, "unit": {"price": 53.33, "per": "per 100g"}, "type": "REGULAR"}, "mainCategory": "Home & Garden/DIY/Adhesives", "image": {"hash": "d8c20be4cbf9a4c50b9aee697cd4a565"}, "packInfo": {}, "type": "REGULAR", "gtin": "5704947000776", "hash": -1372054271}, {"sku": "534150011", "name": "Home Essentials Kettle 1.7L", "brand": {"id": "186278", "name": "Morrisons Home Essentials"}, "price": {"current": 8.0, "lpp": false, "unit": {"price": 0.0, "per": "each"}, "type": "REGULAR"}, "mainCategory": "Home & Garden/Kitchen/Small Appliances /Kettles ", "image": {"hash": "101d3e9513d64c31b2bedcc52baf9e57"}, "reviewStats": {"averageRate": 1.0, "count": 2}, "packInfo": {}, "type": "REGULAR", "gtin": "5010525159515", "hash": 1704291847}, {"sku": "534151011", "name": "Home Essentials 2 Slice Toaster", "brand": {"id": "186278", "name": "Morrisons Home Essentials"}, "price": {"current": 8.0, "lpp": false, "unit": {"price": 0.0, "per": "each"}, "type": "REGULAR"}, "mainCategory": "Home & Garden/Kitchen/Small Appliances /Toasters", "image": {"hash": "9e3b840c63504c7a4ba23ac7b6f11f0f"}, "reviewStats": {"averageRate": 2.299999952316284, "count": 3}, "packInfo": {}, "type": "REGULAR", "gtin": "5010525081335", "hash": 1764565119}, {"sku": "536909011", "name": "Morrisons Grey Striped Supersoft Bath Towel", "brand": {"id": "108397", "name": "Morrisons"}, "price": {"current": 8.0, "lpp": false, "unit": {"price": 0.0, "per": "each"}, "type": "REGULAR"}, "mainCategory": "Home & Garden/Bathroom/Towel, Bathrobes & Bath Mats", "image": {"hash": "0de679defa28321fb0de5afbaa812cd6"}, "packInfo": {}, "type": "REGULAR", "gtin": "5010525053226", "hash": 1887638382}, {"sku": "544086011", "name": "Morrisons 12 Inch Plastic Arundel Clock", "brand": {"id": "108397", "name": "Morrisons"}, "price": {"current": 8.0, "lpp": false, "unit": {"price": 0.0, "per": "each"}, "type": "REGULAR"}, "mainCategory": "Home & Garden/BBQ, Garden & Outdoor Living/Candles, Outdoor Lighting & Decor/Decor", "image": {"hash": "95a4c1da691ed1af17c41ca0700dff81"}, "packInfo": {}, "type": "REGULAR", "gtin": "5010525103464", "hash": 494373210}, {"sku": "544306011", "name": "Morrisons Supersoft Blue Stripe Bath Mat", "brand": {"id": "108397", "name": "Morrisons"}, "price": {"current": 8.0, "lpp": false, "unit": {"price": 0.0, "per": "each"}, "type": "REGULAR"}, "mainCategory": "Home & Garden/Bathroom/Towel, Bathrobes & Bath Mats", "image": {"hash": "19d53d021a892757c3faed8d5a2a91fd"}, "packInfo": {}, "type": "REGULAR", "gtin": "5010525100890", "hash": 417196585}, {"sku": "546741011", "name": "Morrisons Wooden Round Paddle Board", "brand": {"id": "108397", "name": "Morrisons"}, "price": {"current": 8.0, "lpp": false, "unit": {"price": 0.0, "per": "each"}, "type": "REGULAR"}, "mainCategory": "Home & Garden/Dining/Serveware", "image": {"hash": "80f565eb2b2d0444c3bcfbb542d50b47"}, "reviewStats": {"averageRate": 1.0, "count": 1}, "packInfo": {}, "type": "REGULAR", "gtin": "5010251886761", "hash": -903483564}, {"sku": "546756011", "name": "Morrisons Countryside Animal Mugs 4 Pack", "brand": {"id": "108397", "name": "Morrisons"}, "catchWeight": "4 per pack", "price": {"current": 8.0, "lpp": false, "unit": {"price": 2.0, "per": "each"}, "type": "REGULAR"}, "mainCategory": "Home & Garden/Dining/Mugs & Cups", "image": {"hash": "a0e992e03322292d3facff75eb825928"}, "reviewStats": {"averageRate": 5.0, "count": 7}, "packInfo": {}, "type": "REGULAR", "gtin": "5010525083568", "hash": -1886696368}, {"sku": "546769011", "name": "Morrisons Black Plastic Large 12 Cup Cafetiere", "brand": {"id": "108397", "name": "Morrisons"}, "price": {"current": 8.0, "lpp": false, "unit": {"price": 0.0, "per": "each"}, "type": "REGULAR"}, "mainCategory": "Home & Garden/Dining/Cafetiere, Teapots & Accessories ", "image": {"hash": "06840aec495c9eb18479e6934f116ff7"}, "packInfo": {}, "type": "REGULAR", "gtin": "5010525083742", "hash": 1979554556}, {"sku": "546808011", "name": "Morrisons Woven Condiment & Cutlery Holder", "brand": {"id": "108397", "name": "Morrisons"}, "price": {"current": 8.0, "lpp": false, "unit": {"price": 0.0, "per": "each"}, "type": "REGULAR"}, "mainCategory": "Home & Garden/BBQ, Garden & Outdoor Living/BBQ, Picnic & Disposable Tableware/Picnic", "image": {"hash": "d7026c444caf44ea95ec2a7e229ebf59"}, "packInfo": {}, "type": "REGULAR", "gtin": "5010525028767", "hash": -183286722}, {"sku": "550651011", "name": "Gorilla Heavy Duty Mounting Tape 25.4Mm X 1.52M", "brand": {"id": "165771", "name": "Gorilla"}, "price": {"current": 8.0, "lpp": false, "unit": {"price": 0.0, "per": "each"}, "type": "REGULAR"}, "mainCategory": "Home & Garden/DIY/Painting & Decorating", "image": {"hash": "17f1fd564545d91ead4c9603d057029b"}, "packInfo": {}, "type": "REGULAR", "gtin": "5704947002503", "hash": 1929828145}, {"sku": "561321011", "name": "Morrisons Navy 100% Cotton Single Fitted Sheet", "brand": {"id": "108397", "name": "Morrisons"}, "price": {"current": 8.0, "lpp": false, "unit": {"price": 0.0, "per": "each"}, "type": "REGULAR"}, "mainCategory": "Home & Garden/Bedroom/Bedsheets", "image": {"hash": "1a66b99db53fc1d4d827cd4018cb57eb"}, "packInfo": {}, "type": "REGULAR", "gtin": "5010525133171", "hash": 480912488}, {"sku": "561346011", "name": "Morrisons Denim Blue 100% Cotton Single Fitted Sheet", "brand": {"id": "108397", "name": "Morrisons"}, "price": {"current": 8.0, "lpp": false, "unit": {"price": 0.0, "per": "each"}, "type": "REGULAR"}, "mainCategory": "Home & Garden/Bedroom/Bedsheets", "image": {"hash": "446f72b598519ac1ff51df4a425a706e"}, "reviewStats": {"averageRate": 1.0, "count": 2}, "packInfo": {}, "type": "REGULAR", "gtin": "5010525101705", "hash": -101115645}, {"sku": "561954011", "name": "Nutmeg Home Ewe & Me Mugs 4 Pack ", "brand": {"id": "160193", "name": "Nutmeg"}, "catchWeight": "4 per pack", "price": {"current": 8.0, "lpp": false, "unit": {"price": 2.0, "per": "each"}, "type": "REGULAR"}, "mainCategory": "Home & Garden/Dining/Mugs & Cups", "image": {"hash": "190b38c71713bb9fcdc2a3d32ad029ff"}, "reviewStats": {"averageRate": 5.0, "count": 2}, "packInfo": {}, "type": "REGULAR", "gtin": "5010525084725", "hash": -714122246}, {"sku": "561964011", "name": "Nutmeg Home Square Marble Double Toothbrush Holder", "brand": {"id": "108397", "name": "Morrisons"}, "price": {"current": 8.0, "lpp": false, "unit": {"price": 0.0, "per": "each"}, "type": "REGULAR"}, "mainCategory": "Home & Garden/Bathroom/Bathroom Accessories", "image": {"hash": "efd66ce300ad36aea3524a2de7548355"}, "packInfo": {}, "type": "REGULAR", "gtin": "5010525101484", "hash": 798248213}, {"sku": "561998011", "name": "Morrisons Blue Stripe 100% Cotton Bath Towel", "brand": {"id": "108397", "name": "Morrisons"}, "price": {"current": 8.0, "lpp": false, "unit": {"price": 0.0, "per": "each"}, "type": "REGULAR"}, "mainCategory": "Home & Garden/Bathroom/Towel, Bathrobes & Bath Mats", "image": {"hash": "7a0ec1160d675976b9277ad479cbb337"}, "packInfo": {}, "type": "REGULAR", "gtin": "5010525135243", "hash": -413212791}, {"sku": "563005011", "name": "Morrisons 70 Pack Tealights Gift Jar", "brand": {"id": "108397", "name": "Morrisons"}, "price": {"current": 8.0, "lpp": false, "unit": {"price": 0.0, "per": "each"}, "type": "REGULAR"}, "mainCategory": "Home & Garden/Candles & Home Fragrance/Tealights", "image": {"hash": "b05aa4b83dc6d7c33fefb4851c3b2bd9"}, "packInfo": {}, "type": "REGULAR", "gtin": "5010525155890", "hash": -786043663}, {"sku": "563021011", "name": "Morrisons Paisley Sculptured Hand Towel", "brand": {"id": "108397", "name": "Morrisons"}, "price": {"current": 8.0, "lpp": false, "unit": {"price": 0.0, "per": "each"}, "type": "REGULAR"}, "mainCategory": "Home & Garden/Bathroom/Towel, Bathrobes & Bath Mats", "image": {"hash": "f01fa564c59ef5b29763116df5ec761b"}, "packInfo": {}, "type": "REGULAR", "gtin": "5010525135335", "hash": 1336528226}, {"sku": "564824011", "name": "Bar-Be-Quick Wood Free Briquettes", "brand": {"id": "108397", "name": "Morrisons"}, "price": {"current": 8.0, "lpp": false, "unit": {"price": 0.0, "per": "each"}, "type": "REGULAR"}, "mainCategory": "Home & Garden/BBQ, Garden & Outdoor Living/BBQ, Picnic & Disposable Tableware/BBQ", "image": {"hash": "334df8a377eede0de6dbee97673e4b84"}, "packInfo": {}, "type": "REGULAR", "gtin": "5012023000177", "hash": -505073599}, {"sku": "570218011", "name": "Morrisons Terrazzo Rainbow Faux Plant", "brand": {"id": "108397", "name": "Morrisons"}, "price": {"current": 8.0, "lpp": false, "unit": {"price": 0.0, "per": "each"}, "type": "REGULAR"}, "mainCategory": "Home & Garden/Bathroom/Bathroom Accessories", "image": {"hash": "75d8f96d82975df54929b61c87529be1"}, "packInfo": {}, "type": "REGULAR", "gtin": "5010525161112", "hash": -2029860695}, {"sku": "570222011", "name": "Morrisons Terrazzo Ceramic Double Toothbrush Holder", "brand": {"id": "108397", "name": "Morrisons"}, "price": {"current": 8.0, "lpp": false, "unit": {"price": 0.0, "per": "each"}, "type": "REGULAR"}, "mainCategory": "Home & Garden/Bathroom/Bathroom Accessories", "image": {"hash": "62bb14b64b789a7c2f6f6953b85633ac"}, "packInfo": {}, "type": "REGULAR", "gtin": "5010525161044", "hash": -1974207322}, {"sku": "571888011", "name": "Nutmeg Home Habitation Sandalwood Square Soy Waxfill Candle", "brand": {"id": "160193", "name": "Nutmeg"}, "price": {"current": 8.0, "lpp": false, "unit": {"price": 0.0, "per": "each"}, "type": "REGULAR"}, "mainCategory": "Home & Garden/Candles & Home Fragrance/Scented Candles", "image": {"hash": "f749a439cc0260c66aac535328ed90a7"}, "packInfo": {}, "type": "REGULAR", "gtin": "5010525171579", "hash": -1088196064}, {"sku": "571894011", "name": "Nutmeg Home Pink Joyful Slogan Glass Pillar Candle", "brand": {"id": "160193", "name": "Nutmeg"}, "price": {"current": 8.0, "lpp": false, "unit": {"price": 0.0, "per": "each"}, "type": "REGULAR"}, "mainCategory": "Home & Garden/Candles & Home Fragrance/Unscented Candles", "image": {"hash": "709c33f7b2a053fb062ff27f079f50d1"}, "packInfo": {}, "type": "REGULAR", "gtin": "5010525171746", "hash": -471305050}, {"sku": "584280011", "name": "Energizer Max Plus AAA", "brand": {"id": "108027", "name": "Energizer"}, "catchWeight": "14 per pack", "price": {"current": 9.0, "previous": 14.0, "lpp": false, "unit": {"price": 0.6429, "per": "each"}, "type": "OFFER"}, "mainCategory": "Home & Garden/Batteries/AAA", "image": {"hash": "977b5f3e31338369d2158f1767f85200"}, "offer": {"id": "1007495871", "text": "Offer price \u00a39, was \u00a312", "type": "REGULAR"}, "labels": ["ON_OFFER"], "packInfo": {}, "type": "REGULAR", "gtin": "7638900437553", "hash": -806019258}, {"sku": "584281011", "name": "Energizer Max Plus AA", "brand": {"id": "108027", "name": "Energizer"}, "catchWeight": "14 per pack", "price": {"current": 9.0, "previous": 14.0, "lpp": false, "unit": {"price": 0.6429, "per": "each"}, "type": "OFFER"}, "mainCategory": "Home & Garden/Batteries/AA", "image": {"hash": "1fab13207e7056b4549a3325c40022cc"}, "offer": {"id": "1007495863", "text": "Offer price \u00a39, was \u00a312", "type": "REGULAR"}, "labels": ["ON_OFFER"], "packInfo": {}, "type": "REGULAR", "gtin": "7638900437393", "hash": 2138147237}, {"sku": "587665011", "name": "Nutmeg Home Embroidered Bee Cushion", "brand": {"id": "160193", "name": "Nutmeg"}, "price": {"current": 9.0, "lpp": false, "unit": {"price": 0.0, "per": "each"}, "type": "REGULAR"}, "mainCategory": "Home & Garden/Bedroom/Cushions & Throws", "image": {"hash": "2e6693660356cbea8e636167fa47c765"}, "packInfo": {}, "type": "REGULAR", "gtin": "5010525176062", "hash": -474600915}, {"sku": "590654011", "name": "Nutmeg Home Digital Scales", "brand": {"id": "160193", "name": "Nutmeg"}, "price": {"current": 9.0, "lpp": false, "unit": {"price": 0.0, "per": "each"}, "type": "REGULAR"}, "mainCategory": "Home & Garden/Kitchen/Baking & Preserving/Weighing, Measuring & Timing", "image": {"hash": "e282145e7ab02240009f96de1c138f52"}, "packInfo": {}, "type": "REGULAR", "gtin": "5010525169835", "hash": -1438896402}, {"sku": "590667011", "name": "Thermos Hydration Bottle Teal 710ml", "brand": {"id": "156343", "name": "Thermos"}, "price": {"current": 9.0, "lpp": false, "unit": {"price": 0.0, "per": "each"}, "type": "REGULAR"}, "mainCategory": "Home & Garden/Kitchen/Food & Drink Storage/Flasks, Jugs & Bottles ", "image": {"hash": "0b8afe59f50f1189cab9654ae0c5280f"}, "packInfo": {}, "type": "REGULAR", "gtin": "5010576632241", "hash": -652661806}, {"sku": "590668011", "name": "Thermos Hydration Bottle Purple 710ml", "brand": {"id": "156343", "name": "Thermos"}, "price": {"current": 9.0, "lpp": false, "unit": {"price": 0.0, "per": "each"}, "type": "REGULAR"}, "mainCategory": "Home & Garden/Kitchen/Food & Drink Storage/Flasks, Jugs & Bottles ", "image": {"hash": "909ae065d0045bf087492e0ae6ce480b"}, "packInfo": {}, "type": "REGULAR", "gtin": "5050897633572", "hash": -1741348946}]