[{"sku": "608217011", "name": "Rubicon Still Pineapple", "brand": {"id": "107566", "name": "Rubicon"}, "catchWeight": "288ml", "price": {"current": 0.69, "lpp": false, "unit": {"price": 0.24, "per": "per 100ml"}, "type": "REGULAR"}, "mainCategory": "World Foods/Asian/Food Cupboard/Drinks", "image": {"hash": "1141086af5fc3a5516a662ffd42ba210"}, "labels": ["NEW"], "packInfo": {}, "type": "REGULAR", "gtin": "5000382113836", "hash": -1696373835}, {"sku": "612058011", "name": "Rubicon Mango", "brand": {"id": "107566", "name": "Rubicon"}, "catchWeight": "288ml", "price": {"current": 0.69, "lpp": false, "unit": {"price": 0.24, "per": "per 100ml"}, "type": "REGULAR"}, "mainCategory": "World Foods/African Caribbean/Food Cupboard/Drinks", "image": {"hash": "ec63bc31c63a1c9df49386c9edd9f560"}, "reviewStats": {"averageRate": 5.0, "count": 1}, "labels": ["NEW"], "packInfo": {}, "type": "REGULAR", "gtin": "5011898002521", "hash": 926013922}, {"sku": "612059011", "name": "Rubicon Mango Drink", "brand": {"id": "107566", "name": "Rubicon"}, "catchWeight": "330ml", "price": {"current": 0.69, "lpp": false, "unit": {"price": 0.209, "per": "per 100ml"}, "type": "REGULAR"}, "mainCategory": "World Foods/African Caribbean/Food Cupboard/Drinks", "image": {"hash": "e06dde5ba088288f314f308aa0412b7c"}, "reviewStats": {"averageRate": 5.0, "count": 1}, "labels": ["NEW"], "packInfo": {}, "type": "REGULAR", "gtin": "5011898002019", "hash": 492352364}, {"sku": "612060011", "name": "Rubicon Guava Drink", "brand": {"id": "107566", "name": "Rubicon"}, "catchWeight": "330ml", "price": {"current": 0.69, "lpp": false, "unit": {"price": 0.209, "per": "per 100ml"}, "type": "REGULAR"}, "mainCategory": "World Foods/African Caribbean/Food Cupboard/Drinks", "image": {"hash": "467af28547fa4c191fcd54e9815c3954"}, "labels": ["NEW"], "packInfo": {}, "type": "REGULAR", "gtin": "5011898005010", "hash": 1383569424}, {"sku": "612064011", "name": "Rubicon Passion Fruit Drink", "brand": {"id": "107566", "name": "Rubicon"}, "catchWeight": "330ml", "price": {"current": 0.69, "lpp": false, "unit": {"price": 0.209, "per": "per 100ml"}, "type": "REGULAR"}, "mainCategory": "World Foods/African Caribbean/Food Cupboard/Drinks", "image": {"hash": "b8d42bf1adf7e104ea98aca9fdb361aa"}, "reviewStats": {"averageRate": 5.0, "count": 1}, "labels": ["NEW"], "packInfo": {}, "type": "REGULAR", "gtin": "5011898001012", "hash": -1676746611}, {"sku": "612065011", "name": "Rubicon Lychee Drink", "brand": {"id": "107566", "name": "Rubicon"}, "catchWeight": "330ml", "price": {"current": 0.69, "lpp": false, "unit": {"price": 0.209, "per": "per 100ml"}, "type": "REGULAR"}, "mainCategory": "World Foods/African Caribbean/Food Cupboard/Drinks", "image": {"hash": "5bab2f76bf7ae85dad9d0ed49697527b"}, "labels": ["NEW"], "packInfo": {}, "type": "REGULAR", "gtin": "5011898003016", "hash": -1267211521}, {"sku": "508277011", "name": "Sunshine Snacks Chee Zees Original ", "brand": {"id": "180511", "name": "Sunshine Snacks"}, "catchWeight": "45g", "price": {"current": 0.69, "previous": 0.85, "lpp": false, "unit": {"price": 1.5342, "per": "per 100g"}, "type": "OFFER"}, "mainCategory": "World Foods/African Caribbean/Food Cupboard/Snacks", "image": {"hash": "50bb5d9ce5947698928364e6a282cd9b"}, "offer": {"id": "1007526477", "text": "Offer price 69p, was 85p", "type": "REGULAR"}, "reviewStats": {"averageRate": 4.0, "count": 3}, "labels": ["ON_OFFER"], "packInfo": {}, "type": "REGULAR", "gtin": "0040032123513", "hash": 1420861949}, {"sku": "584890011", "name": "Hell Energy Drink Classic", "brand": {"id": "186351", "name": "Hell"}, "catchWeight": "250ml", "price": {"current": 0.7, "lpp": false, "unit": {"price": 0.28, "per": "per 100ml"}, "type": "REGULAR"}, "mainCategory": "Health, Wellbeing & Medicines/Sports Nutrition/Bars & Snacks", "image": {"hash": "77c5794107553866846c40c8b22c955b"}, "packInfo": {}, "type": "REGULAR", "gtin": "5999884034469", "hash": 468224992}, {"sku": "234011011", "name": "Samai Naturally Sweet Plantain Chips", "brand": {"id": "150444", "name": "Samai"}, "catchWeight": "75g", "price": {"current": 0.75, "previous": 0.85, "lpp": false, "unit": {"price": 0.9971, "per": "per 100g"}, "type": "OFFER"}, "mainCategory": "World Foods/African Caribbean/Food Cupboard/Snacks", "image": {"hash": "75e574cdceef280ba158c03dd73015b9"}, "offer": {"id": "1007523629", "text": "Offer price 75p, was 85p", "type": "REGULAR"}, "reviewStats": {"averageRate": 3.299999952316284, "count": 7}, "labels": ["ON_OFFER"], "packInfo": {}, "type": "REGULAR", "gtin": "0832697000595", "hash": 2039684078}, {"sku": "234012011", "name": "Samai Pacific Sea Salt Plantain Chips", "brand": {"id": "150444", "name": "Samai"}, "catchWeight": "75g", "price": {"current": 0.75, "previous": 0.85, "lpp": false, "unit": {"price": 0.9971, "per": "per 100g"}, "type": "OFFER"}, "mainCategory": "World Foods/African Caribbean/Food Cupboard/Snacks", "image": {"hash": "8609fb338ce5fe4c2984cbd91bb3f350"}, "offer": {"id": "1007523621", "text": "Offer price 75p, was 85p", "type": "REGULAR"}, "reviewStats": {"averageRate": 3.4000000953674316, "count": 9}, "labels": ["ON_OFFER"], "packInfo": {"vegetarian": true}, "type": "REGULAR", "gtin": "832697000564", "hash": -1011251169}]